iwcs/__init__.py
iwcs-0.0.4.dist-info/LICENSE
iwcs-0.0.4.dist-info/METADATA
iwcs-0.0.4.dist-info/WHEEL
iwcs-0.0.4.dist-info/top_level.txt
iwcs-0.0.4.dist-info/RECORD
