Metadata-Version: 2.1
Name: iwcs
Version: 0.0.4
Summary: iw client stats, get connected wireless client connection statistics
Home-page: https://github.com/manbehindthemadness/iwcs
Author: Manbehindthemadness
Author-email: manbehindthemadness@gmail.com
Classifier: Programming Language :: Python :: 3
Classifier: License :: OSI Approved :: MIT License
Classifier: Operating System :: OS Independent
Requires-Python: >=3.5
License-File: LICENSE
